README.rst
setup.py
libsam/__init__.py
libsam/samparser.py
libsam.egg-info/PKG-INFO
libsam.egg-info/SOURCES.txt
libsam.egg-info/dependency_links.txt
libsam.egg-info/top_level.txt