Metadata-Version: 1.1
Name: libsam
Version: 0.1.6
Summary: Bio-Informatics sam file libraries.
Home-page: https://github.com/dlmeduLi/libsam
Author: dlmeduLi
Author-email: dlmeduLi@163.com
License: BSD
Keywords: bioinformatic samfile parser
Platform: UNKNOWN
Classifier: Development Status :: 3 - Alpha
Classifier: Topic :: Scientific/Engineering :: Bio-Informatics
Classifier: License :: OSI Approved :: BSD License
